[
    {

      "title": "iRecipe",
      "github": "https://github.com/samueltuki/iRecipe",
      "deployed": "https://samueltuki.github.io/iRecipe/",
      "description": "iRecipe is a real-world front-end application recipe and food image generator app that provides users with access to a large collection of recipes and corresponding images, including international dishes."
    },
    {
        "title": "Project 2",
        "github": "link to github",
        "deployed": "link to deployed page",
        "description": "describe the project"
    },
    {
        "title": "Project 3",
        "github": "link to github",
        "deployed": "link to deployed page",
        "description": "describe the project"
    },
    {
        "title": "Project 4",
        "github": "link to github",
        "deployed": "link to deployed page",
        "description": "describe the project"
    },
    {
        "title": "Project 5",
        "github": "link to github",
        "deployed": "link to deployed page",
        "description": "describe the project"
    },
    {
        "title": "Project 6",
        "github": "link to github",
        "deployed": "link to deployed page",
        "description": "describe the project"
    }
  ]